ory_keto_client/__init__.py
ory_keto_client/api_client.py
ory_keto_client/api_response.py
ory_keto_client/configuration.py
ory_keto_client/exceptions.py
ory_keto_client/py.typed
ory_keto_client/rest.py
ory_keto_client/api/__init__.py
ory_keto_client/api/metadata_api.py
ory_keto_client/api/permission_api.py
ory_keto_client/api/relationship_api.py
ory_keto_client/models/__init__.py
ory_keto_client/models/batch_check_permission_body.py
ory_keto_client/models/batch_check_permission_result.py
ory_keto_client/models/check_opl_syntax_result.py
ory_keto_client/models/check_permission_result.py
ory_keto_client/models/check_permission_result_with_error.py
ory_keto_client/models/create_relationship_body.py
ory_keto_client/models/error_generic.py
ory_keto_client/models/expanded_permission_tree.py
ory_keto_client/models/generic_error.py
ory_keto_client/models/get_version200_response.py
ory_keto_client/models/health_not_ready_status.py
ory_keto_client/models/health_status.py
ory_keto_client/models/is_alive200_response.py
ory_keto_client/models/is_ready503_response.py
ory_keto_client/models/namespace.py
ory_keto_client/models/parse_error.py
ory_keto_client/models/post_check_permission_body.py
ory_keto_client/models/post_check_permission_or_error_body.py
ory_keto_client/models/relation_query.py
ory_keto_client/models/relationship.py
ory_keto_client/models/relationship_namespaces.py
ory_keto_client/models/relationship_patch.py
ory_keto_client/models/relationships.py
ory_keto_client/models/source_position.py
ory_keto_client/models/subject_set.py
ory_keto_client/models/version.py
ory_keto_client-25.4.0.dist-info/LICENSE
ory_keto_client-25.4.0.dist-info/METADATA
ory_keto_client-25.4.0.dist-info/WHEEL
ory_keto_client-25.4.0.dist-info/top_level.txt
ory_keto_client-25.4.0.dist-info/RECORD
